dwc/__init__.py
dwc/__main__.py
dwc/balloontip.py
dwc/bing_wallpaper_changer.py
dwc/constants.py
dwc/debug.py
dwc/desktoppr_wallpaper_changer.py
dwc/dwc.py
dwc/main.py
dwc/natgeopod_wallpaper_changer.py
dwc/pod_wallpaper_changer.py
dwc/unsplash_wallpaper_changer.py
dwc/utils.py
dwc/sources/__init__.py
dwc/sources/bing.py
dwc/sources/desktoppr.py
dwc/sources/nasa_pod.py
dwc/sources/natgeo_pod.py
dwc/sources/unsplash.py
tests/__init__.py
tests/test_debug.py
dtwc-0.0.2.dist-info/LICENSE.md
dtwc-0.0.2.dist-info/METADATA
dtwc-0.0.2.dist-info/WHEEL
dtwc-0.0.2.dist-info/entry_points.txt
dtwc-0.0.2.dist-info/top_level.txt
dtwc-0.0.2.dist-info/RECORD
