Metadata-Version: 2.1
Name: dtwc
Version: 0.0.2
Summary: Change your desktop wallpaper daily!
Home-page: https://github.com/ayan-b/Desktop-Wallpaper-Changer
Author: Ayan Banerjee
Author-email: ayanbanerjee7777@gmail.com
License: MIT
Keywords: wallpaper,customization,personalization
Platform: UNKNOWN
Requires-Python: >=3.5
Requires-Dist: requests (>=2.20.1)
Requires-Dist: Pillow (>=5.2.0)
Requires-Dist: beautifulsoup4 (>=4.6.0)
Requires-Dist: pywin32 (>=223) ; sys_platform == "win32"
